tesis_tn/__init__.py
tesis_tn/main.py
tesis_tn-0.3.dist-info/METADATA
tesis_tn-0.3.dist-info/WHEEL
tesis_tn-0.3.dist-info/top_level.txt
tesis_tn-0.3.dist-info/RECORD
