Metadata-Version: 2.1
Name: tesis_tn
Version: 0.3
Summary: UNKNOWN
Home-page: UNKNOWN
License: MIT
Platform: UNKNOWN
